[
    {
      "title":"Arriadia",
      "image":"https://i.imgur.com/FOXP0T1.jpg",
      "play":"http://cdnamd-hls-globecast.akamaized.net/live/ramdisk/arriadia/hls_snrt/index.m3u8"
    },
    {
      "title":"Alaoula Laayoune",
      "image":"http://i.imgur.com/TOzffM5.jpg",
      "play":"http://cdnamd-hls-globecast.akamaized.net/live/ramdisk/al_aoula_laayoune/hls_snrt/index.m3u8"
    },
    {
      "title":"Alaoula Inter",
       "image":"http://i.imgur.com/8WiJGEY.jpg",
       "play":"http://cdn-hls.globecast.tv/live/ramdisk/al_aoula_inter/hls_snrt/index.m3u8"
    },
    {
      "title":"Assadissa",
      "image":"http://i.imgur.com/5JgvLVq.jpg",
      "play":"http://cdnamd-hls-globecast.akamaized.net/live/ramdisk/assadissa/hls_snrt/index.m3u8"
    },
    {
      "title":"Arrabiaa",
      "image":"http://i.imgur.com/3NeBFJi.jpg",
      "play":"http://cdnamd-hls-globecast.akamaized.net/live/ramdisk/arrabiaa/hls_snrt/arrabiaa-avc1_1000000=3-mp4a_130400_qad=1.m3u8"
    },
    {
      "title":"AlMaghribia",
      "play":"http://cdnamd-hls-globecast.akamaized.net/live/ramdisk/al_maghribia_snrt/hls_snrt/al_maghribia_snrt-avc1_1000000=3-mp4a_130400_qad=1.m3u8",
      "image":"http://i.imgur.com/xjolLBY.jpg"
    }
]
